simple_plotter4a/__init__.py
simple_plotter4a/_version.py
simple_plotter4a/main.py
simple_plotter4a/data/attributions_android_0.1.0.txt
simple_plotter4a/data/attributions_python_0.1.0.txt
simple_plotter4a/data/icon.png
simple_plotter4a/data/icon.svg
simple_plotter4a/data/presplash.png
simple_plotter4a/data/presplash.svg
simple_plotter4a-0.1.0.dist-info/LICENSE
simple_plotter4a-0.1.0.dist-info/METADATA
simple_plotter4a-0.1.0.dist-info/NOTICE
simple_plotter4a-0.1.0.dist-info/WHEEL
simple_plotter4a-0.1.0.dist-info/entry_points.txt
simple_plotter4a-0.1.0.dist-info/top_level.txt
simple_plotter4a-0.1.0.dist-info/RECORD
