Metadata-Version: 2.1
Name: simple-plotter4a
Version: 0.1.0
Summary: kivy based / Android optimized front-end for simple_plotter
Home-page: https://simple-plotter.readthedocs.io/en/latest/
Author: Thies Hecker
Author-email: thies.hecker@gmx.de
License: GPL3
Project-URL: Documentation, https://simple-plotter.readthedocs.io/
Project-URL: Source Code, https://gitlab.com/thecker/simple-plotter4a/
Keywords: kivy Android plot plotting gui front-end
Platform: UNKNOWN
Classifier: License :: OSI Approved :: GNU General Public License v3 (GPLv3)
Requires-Python: >=3
Requires-Dist: simple-plotter (>=0.3)
Requires-Dist: kivy (>=1.11)
Provides-Extra: all
Requires-Dist: matplotlib (>=2) ; extra == 'all'
Requires-Dist: kivy-garden.graph (>=0.4) ; extra == 'all'
Provides-Extra: kivy-garden-graph
Requires-Dist: kivy-garden.graph (>=0.4) ; extra == 'kivy-garden-graph'
Provides-Extra: kivy-matplotlib
Requires-Dist: matplotlib (>=2) ; extra == 'kivy-matplotlib'
